[
    {
        "Title": "Inou-Battle wa Nichijou-kei no Naka de",
        "English Title": "When Supernatural Battles Became Commonplace",
        "Cover Art": "https://cdn.myanimelist.net/images/anime/8/67047.jpg",
        "Score": 7.06,
        "ID": 25159
    },
    {
        "Title": "Yahari Ore no Seishun Love Comedy wa Machigatteiru. Zoku OVA",
        "English Title": "My Teen Romantic Comedy SNAFU TOO! OVA",
        "Cover Art": "https://cdn.myanimelist.net/images/anime/13/84052.jpg",
        "Score": 8.03,
        "ID": 33161
    },
    {
        "Title": "Queen's Blade: Utsukushiki Toushi-tachi",
        "English Title": "Queen's Blade: Beautiful Warriors",
        "Cover Art": "https://cdn.myanimelist.net/images/anime/11/34325.jpg",
        "Score": 6.53,
        "ID": 8456
    },
    {
        "Title": "Violet Evergarden: Recollections",
        "English Title": "Violet Evergarden: Recollections",
        "Cover Art": "https://cdn.myanimelist.net/images/anime/1220/131436.jpg",
        "Score": 8.19,
        "ID": 53672
    },
    {
        "Title": "Naruto",
        "English Title": "Naruto",
        "Cover Art": "https://cdn.myanimelist.net/images/anime/13/17405.jpg",
        "Score": 7.99,
        "ID": 20
    }
]